jax_flash_attn2/__init__.py
jax_flash_attn2/flash_attention.py
jax_flash_attn2/flash_attention_jax/__init__.py
jax_flash_attn2/flash_attention_jax/_backward_jax.py
jax_flash_attn2/flash_attention_jax/_flash_attention.py
jax_flash_attn2/flash_attention_jax/_forward_jax.py
jax_flash_attn2/flash_attention_triton/__init__.py
jax_flash_attn2/flash_attention_triton/_backward_triton.py
jax_flash_attn2/flash_attention_triton/_flash_attention.py
jax_flash_attn2/flash_attention_triton/_forward_triton.py
jax_flash_attn2/flash_attention_triton/_utils.py
jax_flash_attn2/refrence_call.py
jax_flash_attn2/utils.py
jax_flash_attn2-0.0.3.dist-info/LICENSE
jax_flash_attn2-0.0.3.dist-info/METADATA
jax_flash_attn2-0.0.3.dist-info/WHEEL
jax_flash_attn2-0.0.3.dist-info/RECORD
