Metadata-Version: 2.3
Name: jax-flash-attn2
Version: 0.0.3
Summary: Flash Attention Implementation with Multiple Backend Support and Sharding This module provides a flexible implementation of Flash Attention with support for different backends (GPU, TPU, CPU) and platforms (Triton, Pallas, JAX).
License: Apache-2.0
Keywords: JAX,Deep Learning,Machine Learning,XLA
Author: Erfan Zare Chavoshi
Author-email: erfanzare810@gmail.com
Requires-Python: >=3.10,<3.14
Classifier: Development Status :: 3 - Alpha
Classifier: Intended Audience :: Developers
Classifier: License :: OSI Approved :: Apache Software License
Classifier: Programming Language :: Python :: 3
Classifier: Programming Language :: Python :: 3.10
Classifier: Programming Language :: Python :: 3.11
Classifier: Programming Language :: Python :: 3.12
Classifier: Programming Language :: Python :: 3.13
Classifier: Programming Language :: Python :: 3.9
Classifier: Topic :: Scientific/Engineering :: Artificial Intelligence
Requires-Dist: eformer (==0.0.15)
Requires-Dist: einops (>=0.8.0,<0.9.0)
Requires-Dist: jax (>=0.4.36)
Requires-Dist: jaxlib (>=0.4.36)
Requires-Dist: triton (>=3.2.0,<3.3.0)
Project-URL: Documentation, https://erfanzar.github.io/jax-flash-attn2
Project-URL: Homepage, https://github.com/erfanzar/jax-flash-attn2
Project-URL: Repository, https://github.com/erfanzar/jax-flash-attn2
